CONTRIBUTING.md
LICENSE
MANIFEST.in
README
README.md
pyproject.toml
setup.cfg
setup.py
c/common/constants.c
c/common/constants.h
c/common/context.c
c/common/context.h
c/common/dictionary.c
c/common/dictionary.h
c/common/dictionary_inc.h
c/common/platform.c
c/common/platform.h
c/common/shared_dictionary.c
c/common/shared_dictionary_internal.h
c/common/static_init.h
c/common/transform.c
c/common/transform.h
c/common/version.h
c/dec/bit_reader.c
c/dec/bit_reader.h
c/dec/decode.c
c/dec/huffman.c
c/dec/huffman.h
c/dec/prefix.c
c/dec/prefix.h
c/dec/prefix_inc.h
c/dec/state.c
c/dec/state.h
c/enc/backward_references.c
c/enc/backward_references.h
c/enc/backward_references_hq.c
c/enc/backward_references_hq.h
c/enc/backward_references_inc.h
c/enc/bit_cost.c
c/enc/bit_cost.h
c/enc/bit_cost_inc.h
c/enc/block_encoder_inc.h
c/enc/block_splitter.c
c/enc/block_splitter.h
c/enc/block_splitter_inc.h
c/enc/brotli_bit_stream.c
c/enc/brotli_bit_stream.h
c/enc/cluster.c
c/enc/cluster.h
c/enc/cluster_inc.h
c/enc/command.c
c/enc/command.h
c/enc/compound_dictionary.c
c/enc/compound_dictionary.h
c/enc/compress_fragment.c
c/enc/compress_fragment.h
c/enc/compress_fragment_two_pass.c
c/enc/compress_fragment_two_pass.h
c/enc/dictionary_hash.c
c/enc/dictionary_hash.h
c/enc/dictionary_hash_inc.h
c/enc/encode.c
c/enc/encoder_dict.c
c/enc/encoder_dict.h
c/enc/entropy_encode.c
c/enc/entropy_encode.h
c/enc/entropy_encode_static.h
c/enc/fast_log.c
c/enc/fast_log.h
c/enc/find_match_length.h
c/enc/hash.h
c/enc/hash_base.h
c/enc/hash_composite_inc.h
c/enc/hash_forgetful_chain_inc.h
c/enc/hash_longest_match64_inc.h
c/enc/hash_longest_match64_simd_inc.h
c/enc/hash_longest_match_inc.h
c/enc/hash_longest_match_quickly_inc.h
c/enc/hash_longest_match_simd_inc.h
c/enc/hash_rolling_inc.h
c/enc/hash_to_binary_tree_inc.h
c/enc/histogram.c
c/enc/histogram.h
c/enc/histogram_inc.h
c/enc/literal_cost.c
c/enc/literal_cost.h
c/enc/matching_tag_mask.h
c/enc/memory.c
c/enc/memory.h
c/enc/metablock.c
c/enc/metablock.h
python/Brotli_Ng.egg-info/PKG-INFO
python/Brotli_Ng.egg-info/SOURCES.txt
python/Brotli_Ng.egg-info/dependency_links.txt
python/Brotli_Ng.egg-info/top_level.txt
